odoo/addons/jsonifier/README.rst
odoo/addons/jsonifier/__init__.py
odoo/addons/jsonifier/__manifest__.py
odoo/addons/jsonifier/exceptions.py
odoo/addons/jsonifier/demo/export_demo.xml
odoo/addons/jsonifier/demo/ir.exports.line.csv
odoo/addons/jsonifier/demo/resolver_demo.xml
odoo/addons/jsonifier/i18n/ca.po
odoo/addons/jsonifier/i18n/es.po
odoo/addons/jsonifier/i18n/it.po
odoo/addons/jsonifier/i18n/jsonifier.pot
odoo/addons/jsonifier/i18n/zh_CN.po
odoo/addons/jsonifier/models/__init__.py
odoo/addons/jsonifier/models/ir_exports.py
odoo/addons/jsonifier/models/ir_exports_line.py
odoo/addons/jsonifier/models/ir_exports_resolver.py
odoo/addons/jsonifier/models/models.py
odoo/addons/jsonifier/models/utils.py
odoo/addons/jsonifier/readme/CONTRIBUTORS.rst
odoo/addons/jsonifier/readme/DESCRIPTION.rst
odoo/addons/jsonifier/readme/USAGE.rst
odoo/addons/jsonifier/security/ir.model.access.csv
odoo/addons/jsonifier/static/description/icon.png
odoo/addons/jsonifier/static/description/index.html
odoo/addons/jsonifier/tests/__init__.py
odoo/addons/jsonifier/tests/test_get_parser.py
odoo/addons/jsonifier/tests/test_helpers.py
odoo/addons/jsonifier/tests/test_ir_exports_line.py
odoo/addons/jsonifier/views/ir_exports_resolver_view.xml
odoo/addons/jsonifier/views/ir_exports_view.xml
odoo14_addon_jsonifier-14.0.1.2.3.dist-info/METADATA
odoo14_addon_jsonifier-14.0.1.2.3.dist-info/WHEEL
odoo14_addon_jsonifier-14.0.1.2.3.dist-info/top_level.txt
odoo14_addon_jsonifier-14.0.1.2.3.dist-info/RECORD
